augustine_text/__init__.py
augustine_text/markov.py
augustine_text/sample_text.py
augustine_text/mseeds/__init__.py
augustine_text/mseeds/blackgate.mseed
augustine_text/mseeds/churchill.mseed
augustine_text/mseeds/lorem.mseed
augustine_text/mseeds/pride.mseed
augustine_text/mseeds/science.mseed
augustine_text/mseeds/space.mseed
augustine_text-0.1.0.dist-info/METADATA
augustine_text-0.1.0.dist-info/WHEEL
augustine_text-0.1.0.dist-info/top_level.txt
augustine_text-0.1.0.dist-info/RECORD
