Metadata-Version: 2.1
Name: augustine-text
Version: 0.1.0
Summary: UNKNOWN
Home-page: https://github.com/kajuberdut/augustine-text
Author: Patrick Shechet
Author-email: patrick.shechet@gmail.com
License: BSD
Platform: UNKNOWN
Classifier: Development Status :: 3 - Alpha
Classifier: License :: OSI Approved :: BSD License
Classifier: Programming Language :: Python :: 3.9
Classifier: Programming Language :: Python :: 3 :: Only
